kv_store_adapter/__init__.py
kv_store_adapter/errors.py
kv_store_adapter/types.py
kv_store_adapter/adapters/pydantic.py
kv_store_adapter/adapters/single_collection.py
kv_store_adapter/stores/__init__.py
kv_store_adapter/stores/base/__init__.py
kv_store_adapter/stores/base/managed.py
kv_store_adapter/stores/base/unmanaged.py
kv_store_adapter/stores/disk/__init__.py
kv_store_adapter/stores/disk/store.py
kv_store_adapter/stores/elasticsearch/__init__.py
kv_store_adapter/stores/elasticsearch/store.py
kv_store_adapter/stores/elasticsearch/utils.py
kv_store_adapter/stores/memory/__init__.py
kv_store_adapter/stores/memory/store.py
kv_store_adapter/stores/null/__init__.py
kv_store_adapter/stores/null/store.py
kv_store_adapter/stores/redis/__init__.py
kv_store_adapter/stores/redis/store.py
kv_store_adapter/stores/simple/__init__.py
kv_store_adapter/stores/simple/json_store.py
kv_store_adapter/stores/simple/store.py
kv_store_adapter/stores/utils/compound.py
kv_store_adapter/stores/utils/managed_entry.py
kv_store_adapter/stores/utils/time_to_live.py
kv_store_adapter/stores/wrappers/__init__.py
kv_store_adapter/stores/wrappers/clamp_ttl.py
kv_store_adapter/stores/wrappers/passthrough_cache.py
kv_store_adapter/stores/wrappers/prefix_collection.py
kv_store_adapter/stores/wrappers/prefix_key.py
kv_store_adapter/stores/wrappers/single_collection.py
kv_store_adapter/stores/wrappers/statistics.py
kv_store_adapter-0.1.2.dist-info/METADATA
kv_store_adapter-0.1.2.dist-info/WHEEL
kv_store_adapter-0.1.2.dist-info/RECORD
