Metadata-Version: 2.4
Name: kv-store-adapter
Version: 0.1.2
Summary: A pluggable interface for KV Stores
Classifier: Development Status :: 3 - Alpha
Classifier: Intended Audience :: Developers
Classifier: License :: OSI Approved :: MIT License
Classifier: Programming Language :: Python :: 3
Classifier: Programming Language :: Python :: 3.10
Classifier: Programming Language :: Python :: 3.11
Classifier: Programming Language :: Python :: 3.12
Classifier: Programming Language :: Python :: 3.13
Classifier: Programming Language :: Python :: 3.14
Requires-Python: >=3.10
Provides-Extra: disk
Requires-Dist: diskcache>=5.6.0; extra == 'disk'
Provides-Extra: elasticsearch
Requires-Dist: aiohttp>=3.12; extra == 'elasticsearch'
Requires-Dist: elasticsearch>=9.0.0; extra == 'elasticsearch'
Provides-Extra: memory
Requires-Dist: cachetools>=6.0.0; extra == 'memory'
Provides-Extra: pydantic
Requires-Dist: pydantic>=2.11.9; extra == 'pydantic'
Provides-Extra: redis
Requires-Dist: redis>=6.0.0; extra == 'redis'
